MANIFEST.in
requirements.txt
setup.py
EzCrypto.egg-info/PKG-INFO
EzCrypto.egg-info/SOURCES.txt
EzCrypto.egg-info/dependency_links.txt
EzCrypto.egg-info/requires.txt
EzCrypto.egg-info/top_level.txt
ezcrypto/__init__.py
ezcrypto/helpers.py
ezcrypto/pki/__init__.py
ezcrypto/pki/rsa.py