Metadata-Version: 1.1
Name: EzCrypto
Version: 0.1b0
Summary: Easy to use wrapper around ryptographic libraries for Python
Home-page: http://github/gnrfan/EzCrypto/
Author: Antonio Ognio
Author-email: antonio@ognio.com
License: UNKNOWN
Platform: UNKNOWN
Classifier: Development Status :: 4 - Beta
Classifier: Intended Audience :: Developers
Classifier: License :: OSI Approved :: BSD License
Classifier: Operating System :: MacOS :: MacOS X
Classifier: Operating System :: Microsoft :: Windows
Classifier: Operating System :: Unix
Classifier: Programming Language :: Python :: 2
Classifier: Programming Language :: Python :: 3
Classifier: Topic :: Software Development :: Libraries :: Python Modules
Classifier: Topic :: Security :: Cryptography
